mkdocs_wavesurfer/__init__.py
mkdocs_wavesurfer/plugin.py
mkdocs_wavesurfer-0.1.1.dist-info/licenses/LICENSE
mkdocs_wavesurfer-0.1.1.dist-info/METADATA
mkdocs_wavesurfer-0.1.1.dist-info/WHEEL
mkdocs_wavesurfer-0.1.1.dist-info/entry_points.txt
mkdocs_wavesurfer-0.1.1.dist-info/top_level.txt
mkdocs_wavesurfer-0.1.1.dist-info/RECORD
